README.md
setup.py
HUFlickrHelper/__init__.py
HUFlickrHelper/image_helper.py
HUFlickrHelper/text_helper.py
HUFlickrHelper.egg-info/PKG-INFO
HUFlickrHelper.egg-info/SOURCES.txt
HUFlickrHelper.egg-info/dependency_links.txt
HUFlickrHelper.egg-info/not-zip-safe
HUFlickrHelper.egg-info/top_level.txt