Metadata-Version: 1.0
Name: HUFlickrHelper
Version: 0.1
Summary: This package provides helper functions to deal with the Flickr8k dataset.
Home-page: https://scm.cms.hu-berlin.de/remysimo/HUFlickrHelper
Author: Simon Remy
Author-email: remysimo@hu-berlin.de
License: MIT
Platform: UNKNOWN
